sec_api_io/__init__.py
sec_api_io/_modidx.py
sec_api_io/abstract_sec_data_retriever.py
sec_api_io/retry.py
sec_api_io/sec_edgar_enums.py
sec_api_io/sec_edgar_utils.py
sec_api_io/secapio_data_retriever.py
sec_api_io-0.0.17.dist-info/LICENSE
sec_api_io-0.0.17.dist-info/METADATA
sec_api_io-0.0.17.dist-info/WHEEL
sec_api_io-0.0.17.dist-info/entry_points.txt
sec_api_io-0.0.17.dist-info/top_level.txt
sec_api_io-0.0.17.dist-info/RECORD
