Metadata-Version: 2.1
Name: sec-api-io
Version: 0.0.17
Summary: Unofficial facade for the sec-api.io, SEC EDGAR 10-Q document downloader
Home-page: https://github.com/Elijas/sec-api-io
Author: Elijas
Author-email: 4084885+Elijas@users.noreply.github.com
License: MIT License
Keywords: nbdev jupyter notebook python
Classifier: Development Status :: 4 - Beta
Classifier: Intended Audience :: Developers
Classifier: Natural Language :: English
Classifier: Programming Language :: Python :: 3.7
Classifier: Programming Language :: Python :: 3.8
Classifier: Programming Language :: Python :: 3.9
Classifier: Programming Language :: Python :: 3.10
Classifier: Programming Language :: Python :: 3.11
Classifier: Programming Language :: Python :: 3.12
Classifier: License :: OSI Approved :: MIT License
Requires-Python: >=3.7
License-File: LICENSE
Requires-Dist: httpx <1.0,>=0.24.1
Requires-Dist: frozendict <3.0,>=2.3.8
Provides-Extra: dev
